xarray_behave/__init__.py
xarray_behave/annot.py
xarray_behave/event_utils.py
xarray_behave/loaders.py
xarray_behave/metrics.py
xarray_behave/xarray_behave.py
xarray_behave/gui/__init__.py
xarray_behave/gui/app.py
xarray_behave/gui/audio_player.py
xarray_behave/gui/das.py
xarray_behave/gui/formbuilder.py
xarray_behave/gui/icon.png
xarray_behave/gui/table.py
xarray_behave/gui/utils.py
xarray_behave/gui/view_dialog.py
xarray_behave/gui/views.py
xarray_behave/gui/widgets.py
xarray_behave/gui/forms/das_make.yaml
xarray_behave/gui/forms/das_predict.yaml
xarray_behave/gui/forms/das_train.yaml
xarray_behave/gui/forms/envelope_computation.yaml
xarray_behave/gui/forms/export_for_das.yaml
xarray_behave/gui/forms/from_dir.yaml
xarray_behave/gui/forms/from_file.yaml
xarray_behave/gui/forms/from_zarr.yaml
xarray_behave/gui/forms/spec_freq.yaml
xarray_behave/io/__init__.py
xarray_behave/io/annotations.py
xarray_behave/io/annotations_manual.py
xarray_behave/io/audio.py
xarray_behave/io/balltracks.py
xarray_behave/io/movieparams.py
xarray_behave/io/poses.py
xarray_behave/io/timestamps.py
xarray_behave/io/tracks.py
xarray_behave/io/samplestamps/__init__.py
xarray_behave/io/samplestamps/samplestamps.py
xarray_behave/io/samplestamps/utils.py
xarray_behave-0.37.4.dist-info/licenses/LICENSE
xarray_behave-0.37.4.dist-info/WHEEL
xarray_behave-0.37.4.dist-info/METADATA
xarray_behave-0.37.4.dist-info/RECORD
